keyring-subprocess.pth
keyring_subprocess.LICENSE
keyring_subprocess/__init__.py
keyring_subprocess/_internal/__init__.py
keyring_subprocess/_internal/loader.py
keyring_subprocess/_internal/seeder.py
keyring_subprocess/_internal/wheels/keyring_subprocess-0.9.0-py3-none-any.whl
keyring_subprocess/_vendor/importlib_metadata/__init__.py
keyring_subprocess/_vendor/importlib_metadata/_adapters.py
keyring_subprocess/_vendor/importlib_metadata/_collections.py
keyring_subprocess/_vendor/importlib_metadata/_compat.py
keyring_subprocess/_vendor/importlib_metadata/_functools.py
keyring_subprocess/_vendor/importlib_metadata/_itertools.py
keyring_subprocess/_vendor/importlib_metadata/_meta.py
keyring_subprocess/_vendor/importlib_metadata/_text.py
keyring_subprocess/_vendor/importlib_metadata/importlib_metadata.LICENSE
keyring_subprocess/_vendor/importlib_metadata/py.typed
keyring_subprocess/_vendor/keyring/__init__.py
keyring_subprocess/_vendor/keyring/__main__.py
keyring_subprocess/_vendor/keyring/backend.py
keyring_subprocess/_vendor/keyring/backends/__init__.py
keyring_subprocess/_vendor/keyring/backends/chainer.py
keyring_subprocess/_vendor/keyring/backends/fail.py
keyring_subprocess/_vendor/keyring/backends/kwallet.py
keyring_subprocess/_vendor/keyring/backends/libsecret.py
keyring_subprocess/_vendor/keyring/backends/macOS/__init__.py
keyring_subprocess/_vendor/keyring/backends/macOS/api.py
keyring_subprocess/_vendor/keyring/backends/null.py
keyring_subprocess/_vendor/keyring/backends/OS_X.py
keyring_subprocess/_vendor/keyring/backends/SecretService.py
keyring_subprocess/_vendor/keyring/backends/Windows.py
keyring_subprocess/_vendor/keyring/cli.py
keyring_subprocess/_vendor/keyring/core.py
keyring_subprocess/_vendor/keyring/credentials.py
keyring_subprocess/_vendor/keyring/devpi_client.py
keyring_subprocess/_vendor/keyring/errors.py
keyring_subprocess/_vendor/keyring/http.py
keyring_subprocess/_vendor/keyring/LICENSE
keyring_subprocess/_vendor/keyring/py.typed
keyring_subprocess-0.11.1.dist-info/entry_points.txt
keyring_subprocess-0.11.1.dist-info/WHEEL
keyring_subprocess-0.11.1.dist-info/METADATA
keyring_subprocess-0.11.1.dist-info/RECORD
