Metadata-Version: 2.1
Name: keyring-subprocess
Version: 0.11.1
Summary: 
Home-page: https://keyring-subprocess.darsstar.dev/
License: MIT
Author: Dos Moonen
Author-email: darsstar@gmail.com
Requires-Python: >=3.7,<4.0
Classifier: License :: OSI Approved :: MIT License
Classifier: Programming Language :: Python :: 3
Classifier: Programming Language :: Python :: 3.10
Classifier: Programming Language :: Python :: 3.7
Classifier: Programming Language :: Python :: 3.8
Classifier: Programming Language :: Python :: 3.9
Provides-Extra: landmark
Provides-Extra: sitecustomize
Requires-Dist: keyring-subprocess-landmark; extra == "landmark"
Requires-Dist: sitecustomize-entrypoints; extra == "sitecustomize"
Project-URL: Repository, https://github.com/Darsstar/keyring-subprocess
